rezide/__init__.py
rezide/get_tree.py
rezide/get_window_sizes.py
rezide/rezide.py
rezide/utils/__init__.py
rezide/utils/config_dir.py
rezide/utils/config_parser.py
rezide/utils/config_readers.py
rezide/utils/dtos.py
rezide/utils/filestore.py
rezide/utils/interfaces.py
rezide/utils/layouts.py
rezide/utils/sway.py
rezide/utils/tiles.py
rezide/utils/tree.py
rezide-0.10.0.dist-info/entry_points.txt
rezide-0.10.0.dist-info/LICENSE
rezide-0.10.0.dist-info/WHEEL
rezide-0.10.0.dist-info/METADATA
rezide-0.10.0.dist-info/RECORD
